Pokeemikarting/__init__.py
Pokeemikarting/pokemon.csv
Pokeemikarting/random_pokemon.py
Pokeemikarting-1.0.1.dist-info/METADATA
Pokeemikarting-1.0.1.dist-info/WHEEL
Pokeemikarting-1.0.1.dist-info/top_level.txt
Pokeemikarting-1.0.1.dist-info/RECORD
