Metadata-Version: 2.1
Name: Pokeemikarting
Version: 1.0.1
Summary: Libreria para generar un Pokemon aleatorio
Author: Emilio Jiminez
Author-email: rochajimenezjoseemilio@gmail.com
Requires-Dist: pandas
